[
  {
    "book_id": "2CH",
    "book_name": "2 Chronicles",
    "chapter": 1,
    "verse": 1,
    "text": "A si mu Solomoni, ọmọ Dafidi, lagbara lori ijọba rẹ̀, Oluwa Ọlọrun rẹ̀ si wà pẹlu rẹ̀, o si gbé e ga gidigidi."
  },
  {
    "book_id": "2CH",
    "book_name": "2 Chronicles",
    "chapter": 1,
    "verse": 2,
    "text": "Solomoni si sọ fun gbogbo Israeli, fun awọn balogun ẹgbẹgbẹrun, ati ọrọrun, ati fun awọn onidajọ, ati fun gbogbo awọn bãlẹ ni gbogbo Israeli, awọn olori awọn baba."
  },
  {
    "book_id": "2CH",
    "book_name": "2 Chronicles",
    "chapter": 1,
    "verse": 3,
    "text": "Solomoni ati gbogbo awọn ijọ enia pẹlu rẹ̀, lọ si ibi giga ti o wà ni Gibeoni; nitori nibẹ ni agọ ajọ enia Ọlọrun gbe wà, ti Mose, iranṣẹ Oluwa ti pa ni aginju."
  },
  {
    "book_id": "2CH",
    "book_name": "2 Chronicles",
    "chapter": 1,
    "verse": 4,
    "text": "Apoti-ẹri Ọlọrun ni Dafidi ti gbé lati Kirjat-jearimu wá si ibi ti Dafidi ti pese silẹ fun u, nitoriti o ti pa agọ kan silẹ fun u ni Jerusalemu."
  },
  {
    "book_id": "2CH",
    "book_name": "2 Chronicles",
    "chapter": 1,
    "verse": 5,
    "text": "Ṣugbọn pẹpẹ idẹ ti Besaleeli, ọmọ Uri, ọmọ Huri, ti ṣe, wà nibẹ niwaju agọ Oluwa: Solomoni ati ijọ enia si wá a ri."
  },
  {
    "book_id": "2CH",
    "book_name": "2 Chronicles",
    "chapter": 1,
    "verse": 6,
    "text": "Solomoni si lọ si ibi pẹpẹ idẹ niwaju Oluwa, ti o ti wà nibi agọ ajọ, o si rú ẹgbẹrun ẹbọ-sisun lori rẹ̀."
  },
  {
    "book_id": "2CH",
    "book_name": "2 Chronicles",
    "chapter": 1,
    "verse": 7,
    "text": "Li oru na li Oluwa fi ara hàn Solomoni, o si wi fun u pe, Bère ohun ti emi o fi fun ọ."
  },
  {
    "book_id": "2CH",
    "book_name": "2 Chronicles",
    "chapter": 1,
    "verse": 8,
    "text": "Solomoni si wi fun Ọlọrun pe, Iwọ ti fi ãnu nla hàn baba mi, o si ti mu mi jọba ni ipò rẹ̀."
  },
  {
    "book_id": "2CH",
    "book_name": "2 Chronicles",
    "chapter": 1,
    "verse": 9,
    "text": "Nisisiyi Oluwa Ọlọrun, jẹ ki a mu ọ̀rọ rẹ fun Dafidi baba mi ṣẹ: nitoriti iwọ ti fi mi jọba lori awọn enia ti o pọ̀ bi erupẹ ilẹ."
  },
  {
    "book_id": "2CH",
    "book_name": "2 Chronicles",
    "chapter": 1,
    "verse": 10,
    "text": "Fun mi li ọgbọ́n ati ìmọ nisisiyi, ki emi le ma wọ ile, ki nsi ma jade niwaju enia yi: nitoripe, tani le ṣe idajọ enia rẹ yi ti o pọ̀ to yi."
  },
  {
    "book_id": "2CH",
    "book_name": "2 Chronicles",
    "chapter": 1,
    "verse": 11,
    "text": "Ọlọrun si wi fun Solomoni pe, Nitoriti eyi wà li aiya rẹ, ti iwọ kò si bère ọrọ̀, ọlà, tabi ọlá, tabi ẹmi awọn ọta rẹ, bẹ̃ni o kò tilẹ bère ẹmi gigun, ṣugbọn o bère ọgbọ́n fun ara rẹ, ki o le ma ṣe idajọ enia mi, lori ẹniti mo fi ọ jọba:"
  },
  {
    "book_id": "2CH",
    "book_name": "2 Chronicles",
    "chapter": 1,
    "verse": 12,
    "text": "Nitorina a fi ọgbọ́n on ìmọ fun ọ, Emi o si fun ọ ni ọrọ̀, ọlá, tabi ọlà, iru eyiti ọba kan ninu awọn ti nwọn wà ṣaju rẹ kò ni ri, bẹ̃ni lẹhin rẹ kì yio si ẹniti yio ni iru rẹ̀."
  },
  {
    "book_id": "2CH",
    "book_name": "2 Chronicles",
    "chapter": 1,
    "verse": 13,
    "text": "Solomoni si pada lati ibi giga ti o wà ni Gibeoni wá si Jerusalemu, lati iwaju agọ ajọ awọn enia, o si jọba lori Israeli."
  },
  {
    "book_id": "2CH",
    "book_name": "2 Chronicles",
    "chapter": 1,
    "verse": 14,
    "text": "Solomoni ko kẹkẹ́ ati awọn ẹlẹṣin jọ: o si ni ẹgbãje kẹkẹ́ ati ẹgbãfa ẹlẹṣin, ti o fi sinu ilu kẹkẹ́ ati pẹlu ọba ni Jerusalemu."
  },
  {
    "book_id": "2CH",
    "book_name": "2 Chronicles",
    "chapter": 1,
    "verse": 15,
    "text": "Ọba si ṣe ki fadakà ati wura ki o wà ni Jerusalemu bi okuta, ati igi kedari li o ṣe ki o dabi igi sikamore ti o wà ni afonifoji fun ọ̀pọlọpọ."
  },
  {
    "book_id": "2CH",
    "book_name": "2 Chronicles",
    "chapter": 1,
    "verse": 16,
    "text": "A si mu ẹṣin wá fun Solomoni lati Egipti, ati okùn-ọ̀gbọ: awọn oniṣowo ọba ngbà okùn-ọ̀gbọ na ni iye kan."
  },
  {
    "book_id": "2CH",
    "book_name": "2 Chronicles",
    "chapter": 1,
    "verse": 17,
    "text": "Nwọn si gòke, nwọn si mu kẹkẹ́ kan lati Egipti wá fun ẹgbẹta ṣekeli fadakà, ati ẹṣin kan fun ãdọjọ: bẹ̃ni nwọn si nmu ẹṣin jade fun gbogbo awọn ọba ara Hitti, ati fun awọn ọba Siria nipa wọn."
  }
]