[
  {
    "book_id": "JOB",
    "book_name": "Job",
    "chapter": 6,
    "verse": 1,
    "text": "JOBU si dahùn o si wipe,"
  },
  {
    "book_id": "JOB",
    "book_name": "Job",
    "chapter": 6,
    "verse": 2,
    "text": "A! a ba le iwọ̀n ibinujẹ mi ninu òṣuwọn, ki a si le igbe ọ̀fọ mi le ori òṣuwọn ṣọkan pọ̀!"
  },
  {
    "book_id": "JOB",
    "book_name": "Job",
    "chapter": 6,
    "verse": 3,
    "text": "Njẹ nisisiyi, iba wuwo jù iyanrin okun lọ: nitorina li ọ̀rọ mi ṣe ntàse."
  },
  {
    "book_id": "JOB",
    "book_name": "Job",
    "chapter": 6,
    "verse": 4,
    "text": "Nitoripe ọfa Olodumare wọ̀ mi ninu, oró eyiti ọkàn mi mu; ipaiya-ẹ̀ru Ọlorun dotì mi."
  },
  {
    "book_id": "JOB",
    "book_name": "Job",
    "chapter": 6,
    "verse": 5,
    "text": "Kẹtẹkẹtẹ ìgbẹ a ma dún, nigbati o ba ni koriko, tabi ọdá-malu a ma dún sori ijẹ rẹ̀?"
  },
  {
    "book_id": "JOB",
    "book_name": "Job",
    "chapter": 6,
    "verse": 6,
    "text": "A le jẹ ohun ti kò li adùn li aini iyọ̀, tabi adùn wà ninu funfun ẹyin?"
  },
  {
    "book_id": "JOB",
    "book_name": "Job",
    "chapter": 6,
    "verse": 7,
    "text": "Ohun ti ọkàn mi kọ̀ lati tọ́, on li o dàbi onjẹ mi ti kò ni adùn."
  },
  {
    "book_id": "JOB",
    "book_name": "Job",
    "chapter": 6,
    "verse": 8,
    "text": "A! emi iba lè ri iberè mi gbà; ati pe, ki Ọlọrun le fi ohun ti emi ṣafẹri fun mi."
  },
  {
    "book_id": "JOB",
    "book_name": "Job",
    "chapter": 6,
    "verse": 9,
    "text": "Ani, Ọlọrun iba jẹ pa mi run, ti on iba jẹ ṣiwọ rẹ̀ ki o si ké mi kuro."
  },
  {
    "book_id": "JOB",
    "book_name": "Job",
    "chapter": 6,
    "verse": 10,
    "text": "Nigbana ni emi iba ni itunú sibẹ, ani emi iba mu ọkàn mi le ninu ibinujẹ mi ti kò da ni si: nitori emi kò fi ọ̀rọ Ẹni Mimọ́ nì sin ri."
  },
  {
    "book_id": "JOB",
    "book_name": "Job",
    "chapter": 6,
    "verse": 11,
    "text": "Kili agbara mi ti emi o fi dabá? ki si li opin mi ti emi o fi fà ẹmi mi gùn?"
  },
  {
    "book_id": "JOB",
    "book_name": "Job",
    "chapter": 6,
    "verse": 12,
    "text": "Agbara mi iṣe agbara okuta bi, tabi ẹran ara mi iṣe idẹ?"
  },
  {
    "book_id": "JOB",
    "book_name": "Job",
    "chapter": 6,
    "verse": 13,
    "text": "Iranlọwọ mi kò ha wà ninu mi: ọgbọn ha ti salọ kuro lọdọ mi bi?"
  },
  {
    "book_id": "JOB",
    "book_name": "Job",
    "chapter": 6,
    "verse": 14,
    "text": "Ẹniti aya rẹ̀ yọ́ danu tan ni a ba ma ṣãnu fun lati ọdọ ọrẹ rẹ̀ wá, ki o má kọ̀ ibẹru Olodumare silẹ̀."
  },
  {
    "book_id": "JOB",
    "book_name": "Job",
    "chapter": 6,
    "verse": 15,
    "text": "Awọn ará mi ṣẹ̀tan bi odò ṣolõ, bi iṣàn gburu omi odò ṣolõ, nwọn ṣàn kọja lọ."
  },
  {
    "book_id": "JOB",
    "book_name": "Job",
    "chapter": 6,
    "verse": 16,
    "text": "Ti o dúdu nitori omi didì, ati nibiti òjo didì gbe lùmọ si."
  },
  {
    "book_id": "JOB",
    "book_name": "Job",
    "chapter": 6,
    "verse": 17,
    "text": "Nigbakũgba ti nwọn ba gboná, nwọn a si yọ́ ṣanlọ, nigbati õrùn ba mú, nwọn si gbẹ kurò ni ipò wọn."
  },
  {
    "book_id": "JOB",
    "book_name": "Job",
    "chapter": 6,
    "verse": 18,
    "text": "Iya ọ̀na wọn a si yipada sapakan, nwọn goke si ibi asan, nwọn si run."
  },
  {
    "book_id": "JOB",
    "book_name": "Job",
    "chapter": 6,
    "verse": 19,
    "text": "Ẹgbẹ ogun Tema nwoye, awọn ọwọ́-èro Seba duro de wọn."
  },
  {
    "book_id": "JOB",
    "book_name": "Job",
    "chapter": 6,
    "verse": 20,
    "text": "Nwọn dãmu, nitoriti nwọn ni abá; nwọn debẹ̀, nwọn si dãmu."
  },
  {
    "book_id": "JOB",
    "book_name": "Job",
    "chapter": 6,
    "verse": 21,
    "text": "Njẹ nisisiyi, ẹnyin dabi wọn; ẹnyin ri irẹ̀silẹ mi, aiya si fò nyin."
  },
  {
    "book_id": "JOB",
    "book_name": "Job",
    "chapter": 6,
    "verse": 22,
    "text": "Emi ha wipe, ẹ mu ohun fun mi wá, tabi pe, ẹ bun mi ni ẹ̀bun ninu ohun ini nyin?"
  },
  {
    "book_id": "JOB",
    "book_name": "Job",
    "chapter": 6,
    "verse": 23,
    "text": "Tabi, ẹ gbà mi li ọwọ ọ̀ta nì, tabi, ẹ rà mi padà kuro lọwọ alagbara nì!"
  },
  {
    "book_id": "JOB",
    "book_name": "Job",
    "chapter": 6,
    "verse": 24,
    "text": "Ẹ kọ́ mi, emi o si pa ẹnu mi mọ́; ki ẹ si mu mi moye ibiti mo gbe ti ṣìna."
  },
  {
    "book_id": "JOB",
    "book_name": "Job",
    "chapter": 6,
    "verse": 25,
    "text": "Wo! bi ọ̀rọ otitọ ti li agbara to! ṣugbọn kini aròye ibawi nyin jasi?"
  },
  {
    "book_id": "JOB",
    "book_name": "Job",
    "chapter": 6,
    "verse": 26,
    "text": "Ẹnyin ṣebi ẹ o ba ọ̀rọ ati ohùn ẹnu ẹniti o taku wi, ti o dabi afẹfẹ."
  },
  {
    "book_id": "JOB",
    "book_name": "Job",
    "chapter": 6,
    "verse": 27,
    "text": "Ani ẹnyin ṣẹ́ gege fun alainibaba, ẹnyin si da iye le ọrẹ nyin."
  },
  {
    "book_id": "JOB",
    "book_name": "Job",
    "chapter": 6,
    "verse": 28,
    "text": "Nitorina ki eyi ki o tó fun nyin: ẹ ma wò mi! nitoripe o hàn gbangba pe: li oju nyin ni emi kì yio ṣeke."
  },
  {
    "book_id": "JOB",
    "book_name": "Job",
    "chapter": 6,
    "verse": 29,
    "text": "Emi bẹ̀ nyin, ẹ pada, ki o má ṣe jasi ẹ̀ṣẹ: ani ẹ si tun pada, are mi mbẹ ninu ọ̀ran yi."
  },
  {
    "book_id": "JOB",
    "book_name": "Job",
    "chapter": 6,
    "verse": 30,
    "text": "Aiṣedede ha wà li ahọn mi? njẹ itọwò ẹnu mi kò kuku le imọ̀ ohun ti o burujù?"
  }
]