[
  {
    "book_id": "DAN",
    "book_name": "Daniel",
    "chapter": 10,
    "verse": 1,
    "text": "LI ọdun kẹta Kirusi, ọba Persia, li a fi ọ̀rọ kan hàn fun Danieli, orukọ ẹniti ijẹ Belteṣassari; otitọ li ọ̀rọ na, ati lãla na tobi, o si mọ̀ ọ̀rọ na, o si moye iran na."
  },
  {
    "book_id": "DAN",
    "book_name": "Daniel",
    "chapter": 10,
    "verse": 2,
    "text": "Li ọjọ wọnni li emi Danieli fi ikãnu ṣọ̀fọ li ọ̀sẹ mẹta gbako."
  },
  {
    "book_id": "DAN",
    "book_name": "Daniel",
    "chapter": 10,
    "verse": 3,
    "text": "Emi kò jẹ onjẹ ti o dara, bẹ̃ni kò si si ẹran tabi ọti-waini ti o wá si ẹnu mi, bẹ̃li emi kò fi ororo kùn ara mi rara, titi ọ̀sẹ mẹta na fi pe."
  },
  {
    "book_id": "DAN",
    "book_name": "Daniel",
    "chapter": 10,
    "verse": 4,
    "text": "Nigbati o di ọjọ kẹrinlelogun oṣu kini, bi mo ti wà li eti odò nla, ti ijẹ Hiddekeli;"
  },
  {
    "book_id": "DAN",
    "book_name": "Daniel",
    "chapter": 10,
    "verse": 5,
    "text": "Nigbana ni mo gbé oju mi soke, mo wò, si kiyesi i, ọkunrin kan ti o wọ̀ aṣọ àla, ẹ̀gbẹ ẹniti a fi wura Ufasi daradara dì li àmure:"
  },
  {
    "book_id": "DAN",
    "book_name": "Daniel",
    "chapter": 10,
    "verse": 6,
    "text": "Ara rẹ̀ pẹlu dabi okuta berili, oju rẹ̀ si dabi manamána, ẹyinju rẹ̀ dabi iná fitila, apa ati ẹsẹ rẹ̀ li awọ̀ ti o dabi idẹ ti a wẹ̀ dan, ohùn ọ̀rọ ẹnu rẹ̀ si dabi ohùn ijọ enia pupọ."
  },
  {
    "book_id": "DAN",
    "book_name": "Daniel",
    "chapter": 10,
    "verse": 7,
    "text": "Emi Danieli nikanṣoṣo li o si ri iran na, awọn ọkunrin ti o si wà pẹlu mi kò ri iran na; ṣugbọn ìwariri nlanla dà bò wọn, tobẹ̃ ti nwọn fi sá lọ lati fi ara wọn pamọ́."
  },
  {
    "book_id": "DAN",
    "book_name": "Daniel",
    "chapter": 10,
    "verse": 8,
    "text": "Nitorina emi nikan li o kù, ti mo si ri iran nla yi, kò si kù agbara ninu mi: ẹwà mi si yipada lara mi di ibajẹ, emi kò si lagbara mọ."
  },
  {
    "book_id": "DAN",
    "book_name": "Daniel",
    "chapter": 10,
    "verse": 9,
    "text": "Sibẹ mo gbọ́ ohùn ọ̀rọ rẹ̀: nigbati mo si gbọ́ ohùn ọ̀rọ rẹ̀, nigbana ni mo dãmu, mo si wà ni idojubolẹ̀."
  },
  {
    "book_id": "DAN",
    "book_name": "Daniel",
    "chapter": 10,
    "verse": 10,
    "text": "Sa si kiyesi i, ọwọ kan kàn mi, ti o gbé mi dide lori ẽkun mi, ati lori atẹlẹwọ mi."
  },
  {
    "book_id": "DAN",
    "book_name": "Daniel",
    "chapter": 10,
    "verse": 11,
    "text": "O si wi fun mi pe, Danieli, iwọ ọkunrin olufẹ gidigidi, ki oye ọ̀rọ ti mo nsọ fun ọ ki o ye ọ, ki o si duro ni ipò rẹ: nitoripe iwọ li a rán mi si nisisiyi. Nigbati on ti sọ̀rọ bayi fun mi, mo dide duro ni ìwariri."
  },
  {
    "book_id": "DAN",
    "book_name": "Daniel",
    "chapter": 10,
    "verse": 12,
    "text": "Nigbana ni o wi fun mi pe, má bẹ̀ru, Danieli: lati ọjọ kini ti iwọ ti fi aiya rẹ si lati moye, ti iwọ si npọ́n ara rẹ loju niwaju Ọlọrun rẹ, a gbọ́ ọ̀rọ rẹ, emi si wá nitori ọ̀rọ rẹ."
  },
  {
    "book_id": "DAN",
    "book_name": "Daniel",
    "chapter": 10,
    "verse": 13,
    "text": "Ṣugbọn balogun ijọba Persia nì dè mi li ọ̀na li ọjọ mọkanlelogun: ṣugbọn, wò o, Mikaeli, ọkan ninu awọn olori balogun wá lati ràn mi lọwọ: emi si di ipò mi mu lọdọ awọn ọba Persia."
  },
  {
    "book_id": "DAN",
    "book_name": "Daniel",
    "chapter": 10,
    "verse": 14,
    "text": "Njẹ nisisiyi, mo de lati mu ọ moye ohun ti yio ba awọn enia rẹ ni ikẹhin ọjọ: nitori ti ọjọ pipọ ni iran na iṣe."
  },
  {
    "book_id": "DAN",
    "book_name": "Daniel",
    "chapter": 10,
    "verse": 15,
    "text": "Nigbati o si ti sọ iru ọ̀rọ bayi fun mi tan, mo dojukọ ilẹ mo si yadi."
  },
  {
    "book_id": "DAN",
    "book_name": "Daniel",
    "chapter": 10,
    "verse": 16,
    "text": "Si wò o, ẹnikan ti jijọ rẹ̀ dabi ti awọn ọmọ enia fi ọwọ kan ète mi: nigbana ni mo ya ẹnu mi, mo si fọhùn, mo si wi fun ẹniti o duro tì mi pe, oluwa mi, niti iran na, irora mi pada sinu mi, emi kò si lagbara mọ."
  },
  {
    "book_id": "DAN",
    "book_name": "Daniel",
    "chapter": 10,
    "verse": 17,
    "text": "Nitoripé bawo ni ọmọ-ọdọ oluwa mi yi yio ti ṣe le ba oluwa mi yi sọ̀rọ? ṣugbọn bi o ṣe temi ni, lojukanna, agbara kò kù ninu mi, bẹ̃ni kò si kù ẽmi ninu mi."
  },
  {
    "book_id": "DAN",
    "book_name": "Daniel",
    "chapter": 10,
    "verse": 18,
    "text": "Nigbana ni ẹnikan ti o ni aworan enia wá o si tun fi ọwọ tọ́ mi, o si mu mi lara le,"
  },
  {
    "book_id": "DAN",
    "book_name": "Daniel",
    "chapter": 10,
    "verse": 19,
    "text": "O si wipe, iwọ ọkunrin olufẹ gidigidi, má bẹ̀ru: alafia ni fun ọ, mu ara le. Ani mu ara le, Nigbati on ba mi sọ̀rọ, a si mu mi lara le, mo si wipe, Ki oluwa mi ki o ma sọ̀rọ, nitoriti iwọ ti mu mi lara le."
  },
  {
    "book_id": "DAN",
    "book_name": "Daniel",
    "chapter": 10,
    "verse": 20,
    "text": "Nigbana ni o wipe, Iwọ, ha mọ̀ idi ohun ti mo tọ̀ ọ wá si? nisisiyi li emi o si yipada lọ iba balogun Persia jà: nigbati emi ba si jade lọ, kiyesi i, balogun Hellene yio wá."
  },
  {
    "book_id": "DAN",
    "book_name": "Daniel",
    "chapter": 10,
    "verse": 21,
    "text": "Ṣugbọn emi o fi eyi ti a kọ sinu iwe otitọ hàn ọ: kò si si ẹniti o ràn mi lọwọ si awọn wọnyi, bikoṣe Mikaeli balogun nyin."
  }
]