[
  {
    "book_id": "JOB",
    "book_name": "Job",
    "chapter": 36,
    "verse": 1,
    "text": "Elihu also proceeded and said:"
  },
  {
    "book_id": "JOB",
    "book_name": "Job",
    "chapter": 36,
    "verse": 2,
    "text": "\"Bear with me a little, and I will show you That [there are] yet words to speak on God's behalf."
  },
  {
    "book_id": "JOB",
    "book_name": "Job",
    "chapter": 36,
    "verse": 3,
    "text": "I will fetch my knowledge from afar; I will ascribe righteousness to my Maker."
  },
  {
    "book_id": "JOB",
    "book_name": "Job",
    "chapter": 36,
    "verse": 4,
    "text": "For truly my words [are] not false; One who is perfect in knowledge [is] with you."
  },
  {
    "book_id": "JOB",
    "book_name": "Job",
    "chapter": 36,
    "verse": 5,
    "text": "\"Behold, God [is] mighty, but despises [no one;] [He is] mighty in strength of understanding."
  },
  {
    "book_id": "JOB",
    "book_name": "Job",
    "chapter": 36,
    "verse": 6,
    "text": "He does not preserve the life of the wicked, But gives justice to the oppressed."
  },
  {
    "book_id": "JOB",
    "book_name": "Job",
    "chapter": 36,
    "verse": 7,
    "text": "He does not withdraw His eyes from the righteous; But [they are] on the throne with kings, For He has seated them forever, And they are exalted."
  },
  {
    "book_id": "JOB",
    "book_name": "Job",
    "chapter": 36,
    "verse": 8,
    "text": "And if [they are] bound in fetters, Held in the cords of affliction,"
  },
  {
    "book_id": "JOB",
    "book_name": "Job",
    "chapter": 36,
    "verse": 9,
    "text": "Then He tells them their work and their transgressions -- That they have acted defiantly."
  },
  {
    "book_id": "JOB",
    "book_name": "Job",
    "chapter": 36,
    "verse": 10,
    "text": "He also opens their ear to instruction, And commands that they turn from iniquity."
  },
  {
    "book_id": "JOB",
    "book_name": "Job",
    "chapter": 36,
    "verse": 11,
    "text": "If they obey and serve [Him,] They shall spend their days in prosperity, And their years in pleasures."
  },
  {
    "book_id": "JOB",
    "book_name": "Job",
    "chapter": 36,
    "verse": 12,
    "text": "But if they do not obey, They shall perish by the sword, And they shall die without knowledge."
  },
  {
    "book_id": "JOB",
    "book_name": "Job",
    "chapter": 36,
    "verse": 13,
    "text": "\" But the hypocrites in heart store up wrath; They do not cry for help when He binds them."
  },
  {
    "book_id": "JOB",
    "book_name": "Job",
    "chapter": 36,
    "verse": 14,
    "text": "They die in youth, And their life [ends] among the perverted persons."
  },
  {
    "book_id": "JOB",
    "book_name": "Job",
    "chapter": 36,
    "verse": 15,
    "text": "He delivers the poor in their affliction, And opens their ears in oppression."
  },
  {
    "book_id": "JOB",
    "book_name": "Job",
    "chapter": 36,
    "verse": 16,
    "text": "\"Indeed He would have brought you out of dire distress, [Into] a broad place where [there is] no restraint; And what is set on your table [would be] full of richness."
  },
  {
    "book_id": "JOB",
    "book_name": "Job",
    "chapter": 36,
    "verse": 17,
    "text": "But you are filled with the judgment due the wicked; Judgment and justice take hold [of you.]"
  },
  {
    "book_id": "JOB",
    "book_name": "Job",
    "chapter": 36,
    "verse": 18,
    "text": "Because [there is] wrath, [beware] lest He take you away with [one] blow; For a large ransom would not help you avoid [it.]"
  },
  {
    "book_id": "JOB",
    "book_name": "Job",
    "chapter": 36,
    "verse": 19,
    "text": "Will your riches, Or all the mighty forces, Keep you from distress?"
  },
  {
    "book_id": "JOB",
    "book_name": "Job",
    "chapter": 36,
    "verse": 20,
    "text": "Do not desire the night, When people are cut off in their place."
  },
  {
    "book_id": "JOB",
    "book_name": "Job",
    "chapter": 36,
    "verse": 21,
    "text": "Take heed, do not turn to iniquity, For you have chosen this rather than affliction."
  },
  {
    "book_id": "JOB",
    "book_name": "Job",
    "chapter": 36,
    "verse": 22,
    "text": "\" Behold, God is exalted by His power; Who teaches like Him?"
  },
  {
    "book_id": "JOB",
    "book_name": "Job",
    "chapter": 36,
    "verse": 23,
    "text": "Who has assigned Him His way, Or who has said, 'You have done wrong'?"
  },
  {
    "book_id": "JOB",
    "book_name": "Job",
    "chapter": 36,
    "verse": 24,
    "text": "\" Remember to magnify His work, Of which men have sung."
  },
  {
    "book_id": "JOB",
    "book_name": "Job",
    "chapter": 36,
    "verse": 25,
    "text": "Everyone has seen it; Man looks on [it] from afar."
  },
  {
    "book_id": "JOB",
    "book_name": "Job",
    "chapter": 36,
    "verse": 26,
    "text": "\"Behold, God [is] great, and we do not know [Him;] Nor can the number of His years [be] discovered."
  },
  {
    "book_id": "JOB",
    "book_name": "Job",
    "chapter": 36,
    "verse": 27,
    "text": "For He draws up drops of water, Which distill as rain from the mist,"
  },
  {
    "book_id": "JOB",
    "book_name": "Job",
    "chapter": 36,
    "verse": 28,
    "text": "Which the clouds drop down [And] pour abundantly on man."
  },
  {
    "book_id": "JOB",
    "book_name": "Job",
    "chapter": 36,
    "verse": 29,
    "text": "Indeed, can [anyone] understand the spreading of clouds, The thunder from His canopy?"
  },
  {
    "book_id": "JOB",
    "book_name": "Job",
    "chapter": 36,
    "verse": 30,
    "text": "Look, He scatters his light upon it, And covers the depths of the sea."
  },
  {
    "book_id": "JOB",
    "book_name": "Job",
    "chapter": 36,
    "verse": 31,
    "text": "For by these He judges the peoples; He gives food in abundance."
  },
  {
    "book_id": "JOB",
    "book_name": "Job",
    "chapter": 36,
    "verse": 32,
    "text": "He covers [His] hands with lightning, And commands it to strike."
  },
  {
    "book_id": "JOB",
    "book_name": "Job",
    "chapter": 36,
    "verse": 33,
    "text": "His thunder declares it, The cattle also, concerning the rising [storm.]"
  }
]