[
  {
    "book_id": "PSA",
    "book_name": "Psalm",
    "chapter": 116,
    "verse": 1,
    "text": "I love GOD because he listened to me, listened as I begged for mercy."
  },
  {
    "book_id": "PSA",
    "book_name": "Psalm",
    "chapter": 116,
    "verse": 2,
    "text": "He listened so intently as I laid out my case before him."
  },
  {
    "book_id": "PSA",
    "book_name": "Psalm",
    "chapter": 116,
    "verse": 3,
    "text": "Death stared me in the face, hell was hard on my heels. Up against it, I didn't know which way to turn;"
  },
  {
    "book_id": "PSA",
    "book_name": "Psalm",
    "chapter": 116,
    "verse": 4,
    "text": "then I called out to GOD for help: \"Please, GOD!\" I cried out. \"Save my life!\""
  },
  {
    "book_id": "PSA",
    "book_name": "Psalm",
    "chapter": 116,
    "verse": 5,
    "text": "GOD is gracious--it is he who makes things right, our most compassionate God."
  },
  {
    "book_id": "PSA",
    "book_name": "Psalm",
    "chapter": 116,
    "verse": 6,
    "text": "GOD takes the side of the helpless; when I was at the end of my rope, he saved me."
  },
  {
    "book_id": "PSA",
    "book_name": "Psalm",
    "chapter": 116,
    "verse": 7,
    "text": "I said to myself, \"Relax and rest. GOD has showered you with blessings."
  },
  {
    "book_id": "PSA",
    "book_name": "Psalm",
    "chapter": 116,
    "verse": 8,
    "text": "Soul, you've been rescued from death; Eye, you've been rescued from tears; And you, Foot, were kept from stumbling.\""
  },
  {
    "book_id": "PSA",
    "book_name": "Psalm",
    "chapter": 116,
    "verse": 9,
    "text": "I'm striding in the presence of GOD, alive in the land of the living!"
  },
  {
    "book_id": "PSA",
    "book_name": "Psalm",
    "chapter": 116,
    "verse": 10,
    "text": "I stayed faithful, though bedeviled, and despite a ton of bad luck,"
  },
  {
    "book_id": "PSA",
    "book_name": "Psalm",
    "chapter": 116,
    "verse": 11,
    "text": "Despite giving up on the human race, saying, \"They're all liars and cheats.\""
  },
  {
    "book_id": "PSA",
    "book_name": "Psalm",
    "chapter": 116,
    "verse": 12,
    "text": "What can I give back to GOD for the blessings he's poured out on me?"
  },
  {
    "book_id": "PSA",
    "book_name": "Psalm",
    "chapter": 116,
    "verse": 13,
    "text": "I'll lift high the cup of salvation--a toast to GOD! I'll pray in the name of GOD;"
  },
  {
    "book_id": "PSA",
    "book_name": "Psalm",
    "chapter": 116,
    "verse": 14,
    "text": "I'll complete what I promised GOD I'd do, and I'll do it together with his people."
  },
  {
    "book_id": "PSA",
    "book_name": "Psalm",
    "chapter": 116,
    "verse": 15,
    "text": "When they arrive at the gates of death, GOD welcomes those who love him."
  },
  {
    "book_id": "PSA",
    "book_name": "Psalm",
    "chapter": 116,
    "verse": 16,
    "text": "Oh, GOD, here I am, your servant, your faithful servant: set me free for your service!"
  },
  {
    "book_id": "PSA",
    "book_name": "Psalm",
    "chapter": 116,
    "verse": 17,
    "text": "I'm ready to offer the thanksgiving sacrifice and pray in the name of GOD."
  },
  {
    "book_id": "PSA",
    "book_name": "Psalm",
    "chapter": 116,
    "verse": 18,
    "text": "I'll complete what I promised GOD I'd do, and I'll do it in company with his people,"
  },
  {
    "book_id": "PSA",
    "book_name": "Psalm",
    "chapter": 116,
    "verse": 19,
    "text": "In the place of worship, in GOD's house, in Jerusalem, GOD's city. Hallelujah!"
  }
]