[
  {
    "book_id": "ECC",
    "book_name": "Ecclesiastes",
    "chapter": 10,
    "verse": 1,
    "text": "OKÚ eṣinṣin o mu ororo-ikunra alapolu bajẹ ki o ma run õrùn buburu: bẹ̃ni wère diẹ wuwo jù ọgbọ́n ati ọlá lọ."
  },
  {
    "book_id": "ECC",
    "book_name": "Ecclesiastes",
    "chapter": 10,
    "verse": 2,
    "text": "Aiya ọlọgbọ́n mbẹ li ọwọ ọtún rẹ̀; ṣugbọn aiya aṣiwère li ọwọ òsi rẹ̀."
  },
  {
    "book_id": "ECC",
    "book_name": "Ecclesiastes",
    "chapter": 10,
    "verse": 3,
    "text": "Ati pẹlu nigbati ẹniti o ṣiwère ba nrìn li ọ̀na, ọgbọ́n rẹ̀ a fò lọ, on a si wi fun olukuluku enia pe aṣiwère li on."
  },
  {
    "book_id": "ECC",
    "book_name": "Ecclesiastes",
    "chapter": 10,
    "verse": 4,
    "text": "Bi ọkàn ijoye ba ru si ọ, máṣe fi ipò rẹ silẹ; nitoripe itũbá ama tù ẹ̀ṣẹ nla."
  },
  {
    "book_id": "ECC",
    "book_name": "Ecclesiastes",
    "chapter": 10,
    "verse": 5,
    "text": "Buburu kan mbẹ ti mo ri labẹ õrùn, bi ìṣina ti o ti ọdọ awọn ijoye wá."
  },
  {
    "book_id": "ECC",
    "book_name": "Ecclesiastes",
    "chapter": 10,
    "verse": 6,
    "text": "A gbe aṣiwère sipò ọlá, awọn ọlọrọ̀ si joko nipò ẹhin."
  },
  {
    "book_id": "ECC",
    "book_name": "Ecclesiastes",
    "chapter": 10,
    "verse": 7,
    "text": "Mo ri awọn ọmọ-ọdọ lori ẹṣin, ati awọn ọmọ-alade nrìn bi ọmọ-ọdọ ni ilẹ."
  },
  {
    "book_id": "ECC",
    "book_name": "Ecclesiastes",
    "chapter": 10,
    "verse": 8,
    "text": "Ẹniti o wà iho ni yio bọ́ sinu rẹ̀; ati ẹniti o si njá ọgbà tútù, ejo yio si bù u ṣán."
  },
  {
    "book_id": "ECC",
    "book_name": "Ecclesiastes",
    "chapter": 10,
    "verse": 9,
    "text": "Ẹnikan ti o nyi okuta ni yio si ti ipa rẹ̀ ni ipalara; ati ẹniti o si nla igi ni yio si wu li ewu."
  },
  {
    "book_id": "ECC",
    "book_name": "Ecclesiastes",
    "chapter": 10,
    "verse": 10,
    "text": "Bi irin ba kújú, ti on kò si pọn oju rẹ̀, njẹ ki on ki o fi agbara si i; ṣugbọn ère ọgbọ́n ni lati fi ọ̀na hàn."
  },
  {
    "book_id": "ECC",
    "book_name": "Ecclesiastes",
    "chapter": 10,
    "verse": 11,
    "text": "Nitõtọ bi ejo ba bu ni ṣán lainitùju; njẹ ère kì yio si fun onitùju."
  },
  {
    "book_id": "ECC",
    "book_name": "Ecclesiastes",
    "chapter": 10,
    "verse": 12,
    "text": "Ọ̀rọ ẹnu ọlọgbọ̀n li ore-ọfẹ; ṣugbọn ète aṣiwère ni yio gbe ara rẹ̀ mì."
  },
  {
    "book_id": "ECC",
    "book_name": "Ecclesiastes",
    "chapter": 10,
    "verse": 13,
    "text": "Ipilẹṣẹ ọ̀rọ ẹnu rẹ̀ ni wère: ati opin ọ̀rọ ẹnu rẹ̀ ni isinwin iparun."
  },
  {
    "book_id": "ECC",
    "book_name": "Ecclesiastes",
    "chapter": 10,
    "verse": 14,
    "text": "Aṣiwère pẹlu kún fun ọ̀rọ pupọ: enia kò le sọ ohun ti yio ṣẹ; ati ohun ti yio wà lẹhin rẹ̀, tali o le wi fun u?"
  },
  {
    "book_id": "ECC",
    "book_name": "Ecclesiastes",
    "chapter": 10,
    "verse": 15,
    "text": "Lãla aṣiwère da olukuluku wọn li agara, nitoriti kò mọ̀ bi a ti lọ si ilu."
  },
  {
    "book_id": "ECC",
    "book_name": "Ecclesiastes",
    "chapter": 10,
    "verse": 16,
    "text": "Egbé ni fun ọ, iwọ ilẹ, nigbati ọba rẹ ba ṣe ọmọde, ti awọn ọmọ-alade rẹ njẹun ni kutukutu."
  },
  {
    "book_id": "ECC",
    "book_name": "Ecclesiastes",
    "chapter": 10,
    "verse": 17,
    "text": "Ibukún ni fun ọ, iwọ ilẹ, nigbati ọba rẹ ba jẹ ọmọ ọlọlá, ti awọn ọmọ-alade rẹ njẹun li akoko ti o yẹ, fun ilera ti kì si iṣe fun ọti amupara!"
  },
  {
    "book_id": "ECC",
    "book_name": "Ecclesiastes",
    "chapter": 10,
    "verse": 18,
    "text": "Nipa ilọra pupọ igi ile a hù; ati nipa ọlẹ ọwọ, ile a si ma jò."
  },
  {
    "book_id": "ECC",
    "book_name": "Ecclesiastes",
    "chapter": 10,
    "verse": 19,
    "text": "Ẹrín li a nsàse fun, ati ọti-waini ni imu inu alãye dùn: owo si ni idahùn ohun gbogbo."
  },
  {
    "book_id": "ECC",
    "book_name": "Ecclesiastes",
    "chapter": 10,
    "verse": 20,
    "text": "Máṣe bu ọba, ki o má ṣe ninu èro rẹ; máṣe bu ọlọrọ̀ ni iyẹwu rẹ; nitoripe ẹiyẹ oju-ọrun yio gbe ohùn na lọ, ohun ti o ni iyẹ-apá yio si sọ ọ̀ran na."
  }
]